monocular_path_prediction/__init__.py
monocular_path_prediction/__main__.py
monocular_path_prediction/depth_estimator.py
monocular_path_prediction/path_planner.py
monocular_path_prediction/pipeline.py
monocular_path_prediction/utils.py
monocular_path_prediction/config/__init__.py
monocular_path_prediction/config/definitions.py
monocular_path_prediction/config/setup_logger.py
monocular_path_prediction/data/__init__.py
monocular_path_prediction/data/point_cloud.py
monocular_path_prediction/sensors/__init__.py
monocular_path_prediction/sensors/setup.py
monocular_path_prediction/sensors/camera/__init__.py
monocular_path_prediction/sensors/camera/__main__.py
monocular_path_prediction/sensors/camera/camera.py
monocular_path_prediction/sensors/camera/camera_intrinsics.py
monocular_path_prediction/sensors/camera/display.py
monocular_path_prediction/sensors/camera/utils.py
monocular_path_prediction/sensors/camera/calibration/__init__.py
monocular_path_prediction/sensors/camera/calibration/__main__.py
monocular_path_prediction/sensors/camera/calibration/calibration.py
monocular_path_prediction/sensors/camera/calibration/detector.py
monocular_path_prediction/sensors/camera/calibration/results.py
monocular_path_prediction/sensors/camera/images/__init__.py
monocular_path_prediction/sensors/camera/images/images.py
monocular_path_prediction/sensors/device/__init__.py
monocular_path_prediction/sensors/device/__main__.py
monocular_path_prediction/sensors/device/arduino.py
monocular_path_prediction/sensors/device/device_info.py
monocular_path_prediction/sensors/device/device_selector.py
monocular_path_prediction/sensors/device/serial_device.py
monocular_path_prediction/sensors/imu/__init__.py
monocular_path_prediction/sensors/imu/__main__.py
monocular_path_prediction/sensors/imu/calibration.py
monocular_path_prediction/sensors/imu/data_classes.py
monocular_path_prediction/sensors/imu/filter.py
monocular_path_prediction/sensors/imu/imu_device.py
monocular_path_prediction-0.2.2.dist-info/METADATA
monocular_path_prediction-0.2.2.dist-info/WHEEL
monocular_path_prediction-0.2.2.dist-info/licenses/LICENSE
monocular_path_prediction-0.2.2.dist-info/RECORD
