Metadata-Version: 2.4
Name: monocular-path-prediction
Version: 0.2.2
Summary: Monocular Path Predition for Exosuits
Project-URL: homepage, https://github.com/TUM-Aries-Lab/monocular-path-prediction
Author-email: Tsmorz <tony.smoragiewicz@tum.de>
License-File: LICENSE
Requires-Python: <3.14,>=3.11
Requires-Dist: jkp-depth-anything-v2>=0.1.1
Requires-Dist: loguru>=0.7.3
Requires-Dist: matplotlib>=3.10.3
Requires-Dist: opencv-python>=4.12.0.88
Requires-Dist: py-imu>=0.0.1
Requires-Dist: pyserial>=3.5
Requires-Dist: scikit-learn>=1.8.0
Requires-Dist: scipy-stubs>=1.16.1.0
Requires-Dist: scipy>=1.16.1
Provides-Extra: dev
Requires-Dist: coveralls>=4.0.1; extra == 'dev'
Requires-Dist: pre-commit>=4.1.0; extra == 'dev'
Requires-Dist: pyright>=1.1.408; extra == 'dev'
Requires-Dist: pytest-cov>=6.0; extra == 'dev'
Requires-Dist: pytest>=8.3; extra == 'dev'
Requires-Dist: ruff>=0.6.9; extra == 'dev'
Provides-Extra: hw
Requires-Dist: adafruit-circuitpython-lis3mdl>=1.2.6; extra == 'hw'
Requires-Dist: adafruit-circuitpython-lsm6ds>=4.6.1; extra == 'hw'
Provides-Extra: no-hw
